emc/__init__.py
emc/async_.py
emc/exceptions.py
emc/util.py
EMC_info-1.5.2.dist-info/LICENSE
EMC_info-1.5.2.dist-info/METADATA
EMC_info-1.5.2.dist-info/WHEEL
EMC_info-1.5.2.dist-info/top_level.txt
EMC_info-1.5.2.dist-info/RECORD
