Metadata-Version: 2.1
Name: EMC-info
Version: 1.5.2
Summary: EarthMC is a large Minecraft server this package lets you get info about things on that server.
Home-page: https://github.com/TheSuperGamer20578/EMC-info/
Author: TheSuperGamer20578
License: UNKNOWN
Platform: UNKNOWN
Classifier: Programming Language :: Python :: 3.8
Classifier: License :: OSI Approved :: GNU General Public License v2 or later (GPLv2+)
Classifier: Operating System :: OS Independent
Classifier: Development Status :: 5 - Production/Stable
Classifier: Intended Audience :: Developers
Classifier: Natural Language :: English
Classifier: Topic :: Games/Entertainment
Classifier: Typing :: Typed
License-File: LICENSE
Requires-Dist: requests
Requires-Dist: shapely
Provides-Extra: async
Requires-Dist: aiohttp ; extra == 'async'
